ffffffff/__init__.py
ffffffff-0.0.1.dist-info/LICENSE
ffffffff-0.0.1.dist-info/METADATA
ffffffff-0.0.1.dist-info/WHEEL
ffffffff-0.0.1.dist-info/top_level.txt
ffffffff-0.0.1.dist-info/zip-safe
ffffffff-0.0.1.dist-info/RECORD
